super_eventbus/__init__.py
super_eventbus/event.py
super_eventbus/event_manager.py
super_eventbus/exceptions/__init__.py
super_eventbus-0.0.3.dist-info/METADATA
super_eventbus-0.0.3.dist-info/WHEEL
super_eventbus-0.0.3.dist-info/licenses/LICENSE
super_eventbus-0.0.3.dist-info/RECORD
