Metadata-Version: 2.1
Name: super-eventbus
Version: 0.0.3
Summary: A python eventbus
Project-URL: Homepage, https://github.com/Gu-ZT/EventBus
Author-email: 古镇天Gugle <gugle@st.xatu.edu.cn>
License: GNU AFFERO GENERAL PUBLIC LICENSE
License-File: LICENSE
Classifier: License :: OSI Approved :: GNU Affero General Public License v3
Classifier: Operating System :: OS Independent
Classifier: Programming Language :: Python :: 3
Requires-Python: >=3.7
